yorbali/__init__.py
yorbali-0.0.2.dist-info/LICENSE
yorbali-0.0.2.dist-info/METADATA
yorbali-0.0.2.dist-info/WHEEL
yorbali-0.0.2.dist-info/top_level.txt
yorbali-0.0.2.dist-info/RECORD
