Metadata-Version: 2.1
Name: yorbali
Version: 0.0.2
Summary: Yorbali package for general-purpose data-processing tools
Home-page: https://github.com/lapyl/yorbali
Author: Lalit Patel
Author-email: llsr@att.net
License: UNKNOWN
Platform: UNKNOWN
Classifier: Programming Language :: Python :: 3
Classifier: License :: OSI Approved :: MIT License
Classifier: Operating System :: OS Independent
Requires-Python: >=3.6
